opium/__init__.py
opium/business.py
opium/config.py
opium/okd.py
opium/opium.py
opium-0.1.1.dist-info/AUTHORS.rst
opium-0.1.1.dist-info/LICENSE
opium-0.1.1.dist-info/METADATA
opium-0.1.1.dist-info/WHEEL
opium-0.1.1.dist-info/entry_points.txt
opium-0.1.1.dist-info/top_level.txt
opium-0.1.1.dist-info/RECORD
