Metadata-Version: 2.1
Name: opium
Version: 0.1.1
Summary: OpenShift Pod Independent Usage Metrics (OPIUM) pulling & aggregating metrics from multiple pods made easy!
Home-page: https://github.com/panagiks/opium
Author: Kolokotronis Panagiotis
Author-email: panagiks@gmail.com
License: MIT license
Keywords: opium
Platform: UNKNOWN
Classifier: Development Status :: 2 - Pre-Alpha
Classifier: Intended Audience :: Developers
Classifier: License :: OSI Approved :: MIT License
Classifier: Natural Language :: English
Classifier: Programming Language :: Python :: 3
Classifier: Programming Language :: Python :: 3.6
Classifier: Programming Language :: Python :: 3.7
Classifier: Programming Language :: Python :: 3.8
Requires-Python: >=3.6
Requires-Dist: aiohttp (==3.7.1)
Requires-Dist: yaab (==0.2.2)
